{"id":"1","pregunta":" Cual de los elementos indicados no es un elemento de HTML5?","respuestas":["center ","audio ","footer ","source "],"contestacion":[" Correcto!"," Incorrecto."," Incorrecto."," Incorrecto."],"correcta":0}
{"id":"2","pregunta":" Indica, cual de las siguientes estructuras de SGML no se utiliza en HTML4","respuestas":["Comentarios ","Entidades ","Instrucciones de procesamiento ","Atributos "],"contestacion":[" Incorrecto."," Incorrecto."," Correcto!"," Incorrecto."],"correcta":2}
{"id":"3","pregunta":" Indicar el elemento de HTML5 mas apropiado para ubicar enlaces externos (articulos o sitios recomendados, redes sociales, etc.)","respuestas":["section ","div ","nav ","aside "],"contestacion":[" Incorrecto."," Incorrecto."," Incorrecto."," Correcto!"],"correcta":3}
{"id":"4","pregunta":" Cual de los atributos de tabla indicados a continuacion no existe en HTML5","respuestas":["summary ","border ","rowspan ","colspan "],"contestacion":[" Correcto!"," Incorrecto."," Incorrecto."," Incorrecto."],"correcta":0}
{"id":"5","pregunta":" Indica cual de los siguientes valores no es valido para el atributo type de un input","respuestas":["\"textarea\" ","\"hidden\" ","\"submit\" ","\"checkbox\" "],"contestacion":[" Correcto!"," Incorrecto."," Incorrecto."," Incorrecto."],"correcta":0}
